{
  "Name": "an Undead Lizard",
  "CorpseNameOverride": "corpse of an Undead Lizard",
  "BaseType": "Server.Mobiles.BaseCreatureTemplate",
  "Str": 290,
  "Int": 300,
  "Dex": 85,
  "ActiveSpeed": 0.2,
  "PassiveSpeed": 0.4,
  "AiType": "AI_Mage",
  "AlwaysMurderer": true,
  "BaseSoundID": 412,
  "Body": 33,
  "CanRummageCorpses": true,
  "CreatureType": "Undead",
  "VirtualArmor": 30,
  "Female": false,
  "FightMode": "Closest",
  "FightRange": 1,
  "HideType": "Lizard",
  "Hides": 5,
  "HitsMax": 290,
  "Hue": 17969,
  "LootItemChance": 75,
  "LootItemLevel": 3,
  "LootTable": "46",
  "ManaMaxSeed": 250,
  "PerceptionRange": 10,
  "SaySpellMantra": true,
  "StamMaxSeed": 80,
  "PreferredSpells": [
    "Server.Spells.First.MagicArrowSpell",
    "Server.Spells.Sixth.EnergyBoltSpell",
    "Server.Spells.Sixth.ExplosionSpell",
    "Server.Spells.Sixth.MassCurseSpell",
    "Server.Spells.Third.FireballSpell"
  ],
  "Resistances": {
    "Poison": 6,
    "MagicImmunity": 3
  },
  "Skills": {
    "MagicResist": 60,
    "Tactics": 70,
    "Magery": 90
  },
  "Attack": {
    "Speed": 40,
    "Damage": {
      "Min": 8,
      "Max": 43
    },
    "HitSound": 414,
    "MissSound": 568
  }
}